caf/base/__init__.py
caf/base/_version.py
caf/base/data_structures.py
caf/base/py.typed
caf/base/segmentation.py
caf/base/segments.py
caf/base/zoning.py
caf/base/seg_translations/age_11_to_age_ntem.csv
caf/base/seg_translations/age_9_to_age_edge.csv
caf/base/seg_translations/age_9_to_age_ntem.csv
caf/base/seg_translations/car_availability_to_norcom_0v1+.csv
caf/base/seg_translations/economic_status_to_status_aps.csv
caf/base/seg_translations/hh_type_to_ca.csv
caf/base/seg_translations/p_to_userclass.csv
caf/base/seg_translations/sic_2_digit_to_sic_1_digit.csv
caf/base/seg_translations/sic_4_digit_to_sic_1_digit.csv
caf/base/seg_translations/sic_4_digit_to_sic_2_digit.csv
caf/base/segments/accom_h.yml
caf/base/segments/accom_hr.yml
caf/base/segments/adult_nssec.yml
caf/base/segments/adults.yml
caf/base/segments/age_11.yml
caf/base/segments/age_5.yml
caf/base/segments/age_9.yml
caf/base/segments/age_edge.yml
caf/base/segments/age_ntem.yml
caf/base/segments/aws.yml
caf/base/segments/ca.yml
caf/base/segments/car_availability.yml
caf/base/segments/children.yml
caf/base/segments/direction.yml
caf/base/segments/direction_od.yml
caf/base/segments/economic_status.yml
caf/base/segments/g.yml
caf/base/segments/gender_3.yml
caf/base/segments/hh_type.yml
caf/base/segments/m.yml
caf/base/segments/norcom_0v1+.yml
caf/base/segments/ns_sec.yml
caf/base/segments/p.yml
caf/base/segments/pop_econ.yml
caf/base/segments/pop_emp.yml
caf/base/segments/sic_1_digit.yml
caf/base/segments/sic_2_digit.yml
caf/base/segments/sic_4_digit.yml
caf/base/segments/soc.yml
caf/base/segments/status_aps.yml
caf/base/segments/total.yml
caf/base/segments/tp.yml
caf/base/segments/uni.yml
caf/base/segments/userclass.yml
caf_base-0.4.0.dist-info/licenses/LICENSE
caf_base-0.4.0.dist-info/METADATA
caf_base-0.4.0.dist-info/WHEEL
caf_base-0.4.0.dist-info/top_level.txt
caf_base-0.4.0.dist-info/RECORD
