Metadata-Version: 2.4
Name: caf.base
Version: 0.4.0
Summary: Core classes and definitions for CAF family of tools.
Author: Transport for the North
License: Copyright © Transport for the North (“TfN”) (2025).
Project-URL: Bug Tracker, https://github.com/Transport-for-the-North/caf.toolkit/issues
Project-URL: Homepage, https://github.com/Transport-for-the-North/caf.toolkit
Project-URL: Source, https://github.com/Transport-for-the-North/caf.toolkit
Classifier: Programming Language :: Python :: 3 :: Only
Classifier: Programming Language :: Python :: 3.11
Classifier: Programming Language :: Python :: 3.12
Classifier: Programming Language :: Python :: 3.13
Requires-Python: >=3.11
License-File: LICENSE
Requires-Dist: numpy>=1.24.3
Requires-Dist: pandas>=2.2
Requires-Dist: caf.toolkit>=0.9.0
Requires-Dist: h5py>=3.9.0
Requires-Dist: pydantic>=2.7
Requires-Dist: scipy>=1.11.3
Requires-Dist: strictyaml>=1.7.3
Requires-Dist: tables>=3.9.1
Provides-Extra: lint
Requires-Dist: black>=22.6.0; extra == "lint"
Requires-Dist: mypy<2.0.0,>=1.0.0; extra == "lint"
Requires-Dist: mypy_extensions<2.0.0,>=1.0.0; extra == "lint"
Requires-Dist: pydocstyle>=6.1.1; extra == "lint"
Requires-Dist: pydocstyle[toml]; extra == "lint"
Requires-Dist: pylint>=2.14.5; extra == "lint"
Provides-Extra: test
Requires-Dist: pytest<9.0.0,>=7.4.0; extra == "test"
Requires-Dist: pytest-cov<7.0.0,>=4.1.0; extra == "test"
Requires-Dist: pytest-xdist<4.0.0,>=3.3.1; extra == "test"
Requires-Dist: tox<4.0.0,>=3.24.3; extra == "test"
Provides-Extra: edit-install
Requires-Dist: versioningit<4.0.0,>=2.2.0; extra == "edit-install"
Dynamic: license-file
